{
 "EndDate": "2019-06-03T00:00:00Z",
 "DataDays": 7,
 "Source": "kubevirt/kubevirt",
 "Data": {
  "AverageRetestsToMerge": {
   "Avg": 0.92,
   "Std": 1.5,
   "DataPoints": [
    {
     "Value": 1,
     "PRs": [
      {
       "Number": 2281,
       "MergedAt": "2019-05-28T09:44:13Z"
      }
     ]
    },
    {
     "Value": 1,
     "PRs": [
      {
       "Number": 2250,
       "MergedAt": "2019-05-29T20:24:54Z"
      }
     ]
    },
    {
     "Value": 0,
     "PRs": [
      {
       "Number": 2332,
       "MergedAt": "2019-05-30T15:53:29Z"
      }
     ]
    },
    {
     "Value": 0,
     "PRs": [
      {
       "Number": 2328,
       "MergedAt": "2019-05-29T11:06:06Z"
      }
     ]
    },
    {
     "Value": 0,
     "PRs": [
      {
       "Number": 2327,
       "MergedAt": "2019-05-29T15:21:22Z"
      }
     ]
    },
    {
     "Value": 0,
     "PRs": [
      {
       "Number": 2299,
       "MergedAt": "2019-05-27T08:13:23Z"
      }
     ]
    },
    {
     "Value": 5,
     "PRs": [
      {
       "Number": 2276,
       "MergedAt": "2019-05-28T11:50:06Z"
      }
     ]
    },
    {
     "Value": 0,
     "PRs": [
      {
       "Number": 2271,
       "MergedAt": "2019-05-28T09:58:15Z"
      }
     ]
    },
    {
     "Value": 0,
     "PRs": [
      {
       "Number": 2323,
       "MergedAt": "2019-05-28T14:02:58Z"
      }
     ]
    },
    {
     "Value": 1,
     "PRs": [
      {
       "Number": 2322,
       "MergedAt": "2019-05-28T09:08:45Z"
      }
     ]
    },
    {
     "Value": 0,
     "PRs": [
      {
       "Number": 2306,
       "MergedAt": "2019-05-27T08:10:31Z"
      }
     ]
    },
    {
     "Value": 3,
     "PRs": [
      {
       "Number": 2301,
       "MergedAt": "2019-05-29T06:25:58Z"
      }
     ]
    }
   ]
  }
 }
}