{
 "EndDate": "2026-06-15T00:00:00Z",
 "DataDays": 7,
 "Source": "kubevirt/kubevirt",
 "Data": {
  "AverageMergeQueueLength": {
   "Avg": 2.71,
   "Std": 3.19,
   "Number": 0,
   "NoRetest": 0,
   "SIGComputeRetest": 0,
   "SIGStorageRetest": 0,
   "SIGNetworkRetest": 0,
   "SIGOperatorRetest": 0,
   "SIGCIRetest": 0,
   "SIGMonitoringRetest": 0,
   "SIGComputeTotal": 0,
   "SIGStorageTotal": 0,
   "SIGNetworkTotal": 0,
   "SIGOperatorTotal": 0,
   "SIGCITotal": 0,
   "SIGMonitoringTotal": 0,
   "QuarantineTotal": 0,
   "QuarantineSigCompute": 0,
   "QuarantineSigNetwork": 0,
   "QuarantineSigStorage": 0,
   "QuarantineSigMonitoring": 0,
   "FailedJobLeaderBoard": null,
   "DataPoints": [
    {
     "Value": 0,
     "Date": "2026-06-15T00:00:00Z"
    },
    {
     "Value": 1,
     "Date": "2026-06-14T00:00:00Z",
     "PRs": [
      {
       "Number": 17923,
       "MergedAt": "2026-06-14T00:42:18Z"
      }
     ]
    },
    {
     "Value": 10,
     "Date": "2026-06-13T00:00:00Z",
     "PRs": [
      {
       "Number": 18077,
       "MergedAt": "2026-06-13T00:28:23Z"
      },
      {
       "Number": 18072,
       "MergedAt": "2026-06-14T14:22:28Z"
      },
      {
       "Number": 18039,
       "MergedAt": "2026-06-13T06:35:41Z"
      },
      {
       "Number": 17996,
       "MergedAt": "2026-06-13T06:35:27Z"
      },
      {
       "Number": 17981,
       "MergedAt": "2026-06-13T06:35:12Z"
      },
      {
       "Number": 17912,
       "MergedAt": "2026-06-13T06:34:50Z"
      },
      {
       "Number": 17884,
       "MergedAt": "2026-06-13T16:10:19Z"
      },
      {
       "Number": 17809,
       "MergedAt": "2026-06-13T06:34:36Z"
      },
      {
       "Number": 17651,
       "MergedAt": "2026-06-13T06:34:29Z"
      },
      {
       "Number": 16990,
       "MergedAt": "2026-06-13T19:26:19Z"
      }
     ]
    },
    {
     "Value": 4,
     "Date": "2026-06-12T00:00:00Z",
     "PRs": [
      {
       "Number": 18039,
       "MergedAt": "2026-06-13T06:35:41Z"
      },
      {
       "Number": 17987,
       "MergedAt": "2026-06-13T00:00:23Z"
      },
      {
       "Number": 17651,
       "MergedAt": "2026-06-13T06:34:29Z"
      },
      {
       "Number": 16990,
       "MergedAt": "2026-06-13T19:26:19Z"
      }
     ]
    },
    {
     "Value": 1,
     "Date": "2026-06-11T00:00:00Z",
     "PRs": [
      {
       "Number": 16990,
       "MergedAt": "2026-06-13T19:26:19Z"
      }
     ]
    },
    {
     "Value": 1,
     "Date": "2026-06-10T00:00:00Z",
     "PRs": [
      {
       "Number": 16990,
       "MergedAt": "2026-06-13T19:26:19Z"
      }
     ]
    },
    {
     "Value": 2,
     "Date": "2026-06-09T00:00:00Z",
     "PRs": [
      {
       "Number": 18009,
       "MergedAt": "2026-06-09T17:55:00Z"
      },
      {
       "Number": 16990,
       "MergedAt": "2026-06-13T19:26:19Z"
      }
     ]
    }
   ]
  }
 }
}