{
 "EndDate": "2026-02-20T18:13:23Z",
 "DataDays": 7,
 "Source": "kubevirt/kubevirt",
 "Data": {
  "AverageMergeQueueLength": {
   "Avg": 4.14,
   "Std": 2.85,
   "Number": 0,
   "NoRetest": 0,
   "SIGComputeRetest": 0,
   "SIGStorageRetest": 0,
   "SIGNetworkRetest": 0,
   "SIGOperatorRetest": 0,
   "SIGCIRetest": 0,
   "SIGMonitoringRetest": 0,
   "SIGComputeTotal": 0,
   "SIGStorageTotal": 0,
   "SIGNetworkTotal": 0,
   "SIGOperatorTotal": 0,
   "SIGCITotal": 0,
   "SIGMonitoringTotal": 0,
   "QuarantineTotal": 0,
   "QuarantineSigCompute": 0,
   "QuarantineSigNetwork": 0,
   "QuarantineSigStorage": 0,
   "QuarantineSigMonitoring": 0,
   "FailedJobLeaderBoard": null,
   "DataPoints": [
    {
     "Value": 1,
     "Date": "2026-02-20T18:13:23Z",
     "PRs": [
      {
       "Number": 16788,
       "MergedAt": "0001-01-01T00:00:00Z"
      }
     ]
    },
    {
     "Value": 6,
     "Date": "2026-02-19T18:13:23Z",
     "PRs": [
      {
       "Number": 16875,
       "MergedAt": "2026-02-19T19:19:31Z"
      },
      {
       "Number": 16852,
       "MergedAt": "2026-02-20T00:55:31Z"
      },
      {
       "Number": 16850,
       "MergedAt": "2026-02-20T06:35:30Z"
      },
      {
       "Number": 16833,
       "MergedAt": "2026-02-19T19:19:23Z"
      },
      {
       "Number": 16818,
       "MergedAt": "2026-02-20T00:55:23Z"
      },
      {
       "Number": 16821,
       "MergedAt": "0001-01-01T00:00:00Z"
      }
     ]
    },
    {
     "Value": 7,
     "Date": "2026-02-18T18:13:23Z",
     "PRs": [
      {
       "Number": 16875,
       "MergedAt": "2026-02-19T19:19:31Z"
      },
      {
       "Number": 16857,
       "MergedAt": "2026-02-19T11:21:32Z"
      },
      {
       "Number": 16850,
       "MergedAt": "2026-02-20T06:35:30Z"
      },
      {
       "Number": 16833,
       "MergedAt": "2026-02-19T19:19:23Z"
      },
      {
       "Number": 16818,
       "MergedAt": "2026-02-20T00:55:23Z"
      },
      {
       "Number": 16792,
       "MergedAt": "2026-02-19T11:21:24Z"
      },
      {
       "Number": 16821,
       "MergedAt": "0001-01-01T00:00:00Z"
      }
     ]
    },
    {
     "Value": 5,
     "Date": "2026-02-17T18:13:23Z",
     "PRs": [
      {
       "Number": 16875,
       "MergedAt": "2026-02-19T19:19:31Z"
      },
      {
       "Number": 16857,
       "MergedAt": "2026-02-19T11:21:32Z"
      },
      {
       "Number": 16833,
       "MergedAt": "2026-02-19T19:19:23Z"
      },
      {
       "Number": 16820,
       "MergedAt": "2026-02-18T11:05:31Z"
      },
      {
       "Number": 16359,
       "MergedAt": "2026-02-18T11:05:23Z"
      }
     ]
    },
    {
     "Value": 8,
     "Date": "2026-02-16T18:13:23Z",
     "PRs": [
      {
       "Number": 16859,
       "MergedAt": "2026-02-16T22:59:21Z"
      },
      {
       "Number": 16855,
       "MergedAt": "2026-02-17T05:31:36Z"
      },
      {
       "Number": 16845,
       "MergedAt": "2026-02-16T22:59:28Z"
      },
      {
       "Number": 16843,
       "MergedAt": "2026-02-17T05:31:28Z"
      },
      {
       "Number": 16840,
       "MergedAt": "2026-02-16T19:19:21Z"
      },
      {
       "Number": 16658,
       "MergedAt": "2026-02-17T05:31:21Z"
      },
      {
       "Number": 16655,
       "MergedAt": "2026-02-16T22:59:21Z"
      },
      {
       "Number": 16359,
       "MergedAt": "2026-02-18T11:05:23Z"
      }
     ]
    },
    {
     "Value": 1,
     "Date": "2026-02-15T18:13:23Z",
     "PRs": [
      {
       "Number": 16475,
       "MergedAt": "2026-02-15T18:55:18Z"
      }
     ]
    },
    {
     "Value": 1,
     "Date": "2026-02-14T18:13:23Z",
     "PRs": [
      {
       "Number": 16758,
       "MergedAt": "2026-02-16T14:19:21Z"
      }
     ]
    }
   ]
  },
  "AverageMergedPRs": {
   "Avg": 5,
   "Std": 0,
   "Number": 0,
   "NoRetest": 0,
   "SIGComputeRetest": 0,
   "SIGStorageRetest": 0,
   "SIGNetworkRetest": 0,
   "SIGOperatorRetest": 0,
   "SIGCIRetest": 0,
   "SIGMonitoringRetest": 0,
   "SIGComputeTotal": 0,
   "SIGStorageTotal": 0,
   "SIGNetworkTotal": 0,
   "SIGOperatorTotal": 0,
   "SIGCITotal": 0,
   "SIGMonitoringTotal": 0,
   "QuarantineTotal": 0,
   "QuarantineSigCompute": 0,
   "QuarantineSigNetwork": 0,
   "QuarantineSigStorage": 0,
   "QuarantineSigMonitoring": 0,
   "FailedJobLeaderBoard": null,
   "DataPoints": [
    {
     "Value": 1,
     "PRs": [
      {
       "Number": 16875,
       "MergedAt": "2026-02-19T19:19:31Z"
      }
     ]
    },
    {
     "Value": 1,
     "PRs": [
      {
       "Number": 16873,
       "MergedAt": "2026-02-17T08:17:23Z"
      }
     ]
    },
    {
     "Value": 1,
     "PRs": [
      {
       "Number": 16859,
       "MergedAt": "2026-02-16T22:59:21Z"
      }
     ]
    },
    {
     "Value": 1,
     "PRs": [
      {
       "Number": 16857,
       "MergedAt": "2026-02-19T11:21:32Z"
      }
     ]
    },
    {
     "Value": 1,
     "PRs": [
      {
       "Number": 16855,
       "MergedAt": "2026-02-17T05:31:36Z"
      }
     ]
    },
    {
     "Value": 1,
     "PRs": [
      {
       "Number": 16852,
       "MergedAt": "2026-02-20T00:55:31Z"
      }
     ]
    },
    {
     "Value": 1,
     "PRs": [
      {
       "Number": 16851,
       "MergedAt": "2026-02-15T18:55:25Z"
      }
     ]
    },
    {
     "Value": 1,
     "PRs": [
      {
       "Number": 16850,
       "MergedAt": "2026-02-20T06:35:30Z"
      }
     ]
    },
    {
     "Value": 1,
     "PRs": [
      {
       "Number": 16847,
       "MergedAt": "2026-02-14T17:33:17Z"
      }
     ]
    },
    {
     "Value": 1,
     "PRs": [
      {
       "Number": 16845,
       "MergedAt": "2026-02-16T22:59:28Z"
      }
     ]
    },
    {
     "Value": 1,
     "PRs": [
      {
       "Number": 16843,
       "MergedAt": "2026-02-17T05:31:28Z"
      }
     ]
    },
    {
     "Value": 1,
     "PRs": [
      {
       "Number": 16840,
       "MergedAt": "2026-02-16T19:19:21Z"
      }
     ]
    },
    {
     "Value": 1,
     "PRs": [
      {
       "Number": 16839,
       "MergedAt": "2026-02-16T14:37:26Z"
      }
     ]
    },
    {
     "Value": 1,
     "PRs": [
      {
       "Number": 16838,
       "MergedAt": "2026-02-16T15:35:23Z"
      }
     ]
    },
    {
     "Value": 1,
     "PRs": [
      {
       "Number": 16837,
       "MergedAt": "2026-02-16T10:11:20Z"
      }
     ]
    },
    {
     "Value": 1,
     "PRs": [
      {
       "Number": 16835,
       "MergedAt": "2026-02-16T14:25:26Z"
      }
     ]
    },
    {
     "Value": 1,
     "PRs": [
      {
       "Number": 16834,
       "MergedAt": "2026-02-16T14:25:26Z"
      }
     ]
    },
    {
     "Value": 1,
     "PRs": [
      {
       "Number": 16833,
       "MergedAt": "2026-02-19T19:19:23Z"
      }
     ]
    },
    {
     "Value": 1,
     "PRs": [
      {
       "Number": 16831,
       "MergedAt": "2026-02-16T14:25:25Z"
      }
     ]
    },
    {
     "Value": 1,
     "PRs": [
      {
       "Number": 16824,
       "MergedAt": "2026-02-13T19:55:25Z"
      }
     ]
    },
    {
     "Value": 1,
     "PRs": [
      {
       "Number": 16820,
       "MergedAt": "2026-02-18T11:05:31Z"
      }
     ]
    },
    {
     "Value": 1,
     "PRs": [
      {
       "Number": 16819,
       "MergedAt": "2026-02-14T12:35:18Z"
      }
     ]
    },
    {
     "Value": 1,
     "PRs": [
      {
       "Number": 16818,
       "MergedAt": "2026-02-20T00:55:23Z"
      }
     ]
    },
    {
     "Value": 1,
     "PRs": [
      {
       "Number": 16810,
       "MergedAt": "2026-02-15T12:03:18Z"
      }
     ]
    },
    {
     "Value": 1,
     "PRs": [
      {
       "Number": 16792,
       "MergedAt": "2026-02-19T11:21:24Z"
      }
     ]
    },
    {
     "Value": 1,
     "PRs": [
      {
       "Number": 16758,
       "MergedAt": "2026-02-16T14:19:21Z"
      }
     ]
    },
    {
     "Value": 1,
     "PRs": [
      {
       "Number": 16722,
       "MergedAt": "2026-02-16T07:11:19Z"
      }
     ]
    },
    {
     "Value": 1,
     "PRs": [
      {
       "Number": 16666,
       "MergedAt": "2026-02-13T19:55:18Z"
      }
     ]
    },
    {
     "Value": 1,
     "PRs": [
      {
       "Number": 16658,
       "MergedAt": "2026-02-17T05:31:21Z"
      }
     ]
    },
    {
     "Value": 1,
     "PRs": [
      {
       "Number": 16656,
       "MergedAt": "2026-02-20T06:35:23Z"
      }
     ]
    },
    {
     "Value": 1,
     "PRs": [
      {
       "Number": 16655,
       "MergedAt": "2026-02-16T22:59:21Z"
      }
     ]
    },
    {
     "Value": 1,
     "PRs": [
      {
       "Number": 16635,
       "MergedAt": "2026-02-14T05:35:18Z"
      }
     ]
    },
    {
     "Value": 1,
     "PRs": [
      {
       "Number": 16475,
       "MergedAt": "2026-02-15T18:55:18Z"
      }
     ]
    },
    {
     "Value": 1,
     "PRs": [
      {
       "Number": 16359,
       "MergedAt": "2026-02-18T11:05:23Z"
      }
     ]
    },
    {
     "Value": 1,
     "PRs": [
      {
       "Number": 16311,
       "MergedAt": "2026-02-20T08:27:25Z"
      }
     ]
    }
   ]
  },
  "AverageRetestsToMerge": {
   "Avg": 1.94,
   "Std": 1.93,
   "Number": 0,
   "NoRetest": 0,
   "SIGComputeRetest": 0,
   "SIGStorageRetest": 0,
   "SIGNetworkRetest": 0,
   "SIGOperatorRetest": 0,
   "SIGCIRetest": 0,
   "SIGMonitoringRetest": 0,
   "SIGComputeTotal": 0,
   "SIGStorageTotal": 0,
   "SIGNetworkTotal": 0,
   "SIGOperatorTotal": 0,
   "SIGCITotal": 0,
   "SIGMonitoringTotal": 0,
   "QuarantineTotal": 0,
   "QuarantineSigCompute": 0,
   "QuarantineSigNetwork": 0,
   "QuarantineSigStorage": 0,
   "QuarantineSigMonitoring": 0,
   "FailedJobLeaderBoard": null,
   "DataPoints": [
    {
     "Value": 2,
     "PRs": [
      {
       "Number": 16855,
       "MergedAt": "2026-02-17T05:31:36Z"
      }
     ]
    },
    {
     "Value": 0,
     "PRs": [
      {
       "Number": 16845,
       "MergedAt": "2026-02-16T22:59:28Z"
      }
     ]
    },
    {
     "Value": 0,
     "PRs": [
      {
       "Number": 16839,
       "MergedAt": "2026-02-16T14:37:26Z"
      }
     ]
    },
    {
     "Value": 0,
     "PRs": [
      {
       "Number": 16834,
       "MergedAt": "2026-02-16T14:25:26Z"
      }
     ]
    },
    {
     "Value": 0,
     "PRs": [
      {
       "Number": 16475,
       "MergedAt": "2026-02-15T18:55:18Z"
      }
     ]
    },
    {
     "Value": 0,
     "PRs": [
      {
       "Number": 16859,
       "MergedAt": "2026-02-16T22:59:21Z"
      }
     ]
    },
    {
     "Value": 1,
     "PRs": [
      {
       "Number": 16850,
       "MergedAt": "2026-02-20T06:35:30Z"
      }
     ]
    },
    {
     "Value": 2,
     "PRs": [
      {
       "Number": 16824,
       "MergedAt": "2026-02-13T19:55:25Z"
      }
     ]
    },
    {
     "Value": 5,
     "PRs": [
      {
       "Number": 16722,
       "MergedAt": "2026-02-16T07:11:19Z"
      }
     ]
    },
    {
     "Value": 3,
     "PRs": [
      {
       "Number": 16311,
       "MergedAt": "2026-02-20T08:27:25Z"
      }
     ]
    },
    {
     "Value": 4,
     "PRs": [
      {
       "Number": 16875,
       "MergedAt": "2026-02-19T19:19:31Z"
      }
     ]
    },
    {
     "Value": 0,
     "PRs": [
      {
       "Number": 16851,
       "MergedAt": "2026-02-15T18:55:25Z"
      }
     ]
    },
    {
     "Value": 0,
     "PRs": [
      {
       "Number": 16843,
       "MergedAt": "2026-02-17T05:31:28Z"
      }
     ]
    },
    {
     "Value": 0,
     "PRs": [
      {
       "Number": 16840,
       "MergedAt": "2026-02-16T19:19:21Z"
      }
     ]
    },
    {
     "Value": 1,
     "PRs": [
      {
       "Number": 16837,
       "MergedAt": "2026-02-16T10:11:20Z"
      }
     ]
    },
    {
     "Value": 0,
     "PRs": [
      {
       "Number": 16835,
       "MergedAt": "2026-02-16T14:25:26Z"
      }
     ]
    },
    {
     "Value": 0,
     "PRs": [
      {
       "Number": 16831,
       "MergedAt": "2026-02-16T14:25:25Z"
      }
     ]
    },
    {
     "Value": 2,
     "PRs": [
      {
       "Number": 16820,
       "MergedAt": "2026-02-18T11:05:31Z"
      }
     ]
    },
    {
     "Value": 2,
     "PRs": [
      {
       "Number": 16655,
       "MergedAt": "2026-02-16T22:59:21Z"
      }
     ]
    },
    {
     "Value": 2,
     "PRs": [
      {
       "Number": 16359,
       "MergedAt": "2026-02-18T11:05:23Z"
      }
     ]
    },
    {
     "Value": 1,
     "PRs": [
      {
       "Number": 16852,
       "MergedAt": "2026-02-20T00:55:31Z"
      }
     ]
    },
    {
     "Value": 3,
     "PRs": [
      {
       "Number": 16810,
       "MergedAt": "2026-02-15T12:03:18Z"
      }
     ]
    },
    {
     "Value": 3,
     "PRs": [
      {
       "Number": 16792,
       "MergedAt": "2026-02-19T11:21:24Z"
      }
     ]
    },
    {
     "Value": 5,
     "PRs": [
      {
       "Number": 16635,
       "MergedAt": "2026-02-14T05:35:18Z"
      }
     ]
    },
    {
     "Value": 0,
     "PRs": [
      {
       "Number": 16873,
       "MergedAt": "2026-02-17T08:17:23Z"
      }
     ]
    },
    {
     "Value": 0,
     "PRs": [
      {
       "Number": 16838,
       "MergedAt": "2026-02-16T15:35:23Z"
      }
     ]
    },
    {
     "Value": 2,
     "PRs": [
      {
       "Number": 16656,
       "MergedAt": "2026-02-20T06:35:23Z"
      }
     ]
    },
    {
     "Value": 3,
     "PRs": [
      {
       "Number": 16857,
       "MergedAt": "2026-02-19T11:21:32Z"
      }
     ]
    },
    {
     "Value": 1,
     "PRs": [
      {
       "Number": 16847,
       "MergedAt": "2026-02-14T17:33:17Z"
      }
     ]
    },
    {
     "Value": 3,
     "PRs": [
      {
       "Number": 16819,
       "MergedAt": "2026-02-14T12:35:18Z"
      }
     ]
    },
    {
     "Value": 2,
     "PRs": [
      {
       "Number": 16666,
       "MergedAt": "2026-02-13T19:55:18Z"
      }
     ]
    },
    {
     "Value": 7,
     "PRs": [
      {
       "Number": 16658,
       "MergedAt": "2026-02-17T05:31:21Z"
      }
     ]
    },
    {
     "Value": 3,
     "PRs": [
      {
       "Number": 16833,
       "MergedAt": "2026-02-19T19:19:23Z"
      }
     ]
    },
    {
     "Value": 5,
     "PRs": [
      {
       "Number": 16818,
       "MergedAt": "2026-02-20T00:55:23Z"
      }
     ]
    },
    {
     "Value": 6,
     "PRs": [
      {
       "Number": 16758,
       "MergedAt": "2026-02-16T14:19:21Z"
      }
     ]
    }
   ]
  },
  "AverageTimeToMerge": {
   "Avg": 0.62,
   "Std": 0.8,
   "Number": 0,
   "NoRetest": 0,
   "SIGComputeRetest": 0,
   "SIGStorageRetest": 0,
   "SIGNetworkRetest": 0,
   "SIGOperatorRetest": 0,
   "SIGCIRetest": 0,
   "SIGMonitoringRetest": 0,
   "SIGComputeTotal": 0,
   "SIGStorageTotal": 0,
   "SIGNetworkTotal": 0,
   "SIGOperatorTotal": 0,
   "SIGCITotal": 0,
   "SIGMonitoringTotal": 0,
   "QuarantineTotal": 0,
   "QuarantineSigCompute": 0,
   "QuarantineSigNetwork": 0,
   "QuarantineSigStorage": 0,
   "QuarantineSigMonitoring": 0,
   "FailedJobLeaderBoard": null,
   "DataPoints": [
    {
     "Value": 0,
     "PRs": [
      {
       "Number": 16831,
       "MergedAt": "2026-02-16T14:25:25Z"
      }
     ]
    },
    {
     "Value": 0.11,
     "PRs": [
      {
       "Number": 16847,
       "MergedAt": "2026-02-14T17:33:17Z"
      }
     ]
    },
    {
     "Value": 0,
     "PRs": [
      {
       "Number": 16835,
       "MergedAt": "2026-02-16T14:25:26Z"
      }
     ]
    },
    {
     "Value": 0.56,
     "PRs": [
      {
       "Number": 16658,
       "MergedAt": "2026-02-17T05:31:21Z"
      }
     ]
    },
    {
     "Value": 0.37,
     "PRs": [
      {
       "Number": 16656,
       "MergedAt": "2026-02-20T06:35:23Z"
      }
     ]
    },
    {
     "Value": 2.94,
     "PRs": [
      {
       "Number": 16635,
       "MergedAt": "2026-02-14T05:35:18Z"
      }
     ]
    },
    {
     "Value": 0.42,
     "PRs": [
      {
       "Number": 16475,
       "MergedAt": "2026-02-15T18:55:18Z"
      }
     ]
    },
    {
     "Value": 0,
     "PRs": [
      {
       "Number": 16873,
       "MergedAt": "2026-02-17T08:17:23Z"
      }
     ]
    },
    {
     "Value": 3.28,
     "PRs": [
      {
       "Number": 16843,
       "MergedAt": "2026-02-17T05:31:28Z"
      }
     ]
    },
    {
     "Value": 0,
     "PRs": [
      {
       "Number": 16839,
       "MergedAt": "2026-02-16T14:37:26Z"
      }
     ]
    },
    {
     "Value": 0,
     "PRs": [
      {
       "Number": 16838,
       "MergedAt": "2026-02-16T15:35:23Z"
      }
     ]
    },
    {
     "Value": 0.62,
     "PRs": [
      {
       "Number": 16655,
       "MergedAt": "2026-02-16T22:59:21Z"
      }
     ]
    },
    {
     "Value": 0.11,
     "PRs": [
      {
       "Number": 16857,
       "MergedAt": "2026-02-19T11:21:32Z"
      }
     ]
    },
    {
     "Value": 0.7,
     "PRs": [
      {
       "Number": 16850,
       "MergedAt": "2026-02-20T06:35:30Z"
      }
     ]
    },
    {
     "Value": 0,
     "PRs": [
      {
       "Number": 16837,
       "MergedAt": "2026-02-16T10:11:20Z"
      }
     ]
    },
    {
     "Value": 0,
     "PRs": [
      {
       "Number": 16819,
       "MergedAt": "2026-02-14T12:35:18Z"
      }
     ]
    },
    {
     "Value": 0.55,
     "PRs": [
      {
       "Number": 16845,
       "MergedAt": "2026-02-16T22:59:28Z"
      }
     ]
    },
    {
     "Value": 0,
     "PRs": [
      {
       "Number": 16834,
       "MergedAt": "2026-02-16T14:25:26Z"
      }
     ]
    },
    {
     "Value": 0,
     "PRs": [
      {
       "Number": 16792,
       "MergedAt": "2026-02-19T11:21:24Z"
      }
     ]
    },
    {
     "Value": 0.07,
     "PRs": [
      {
       "Number": 16758,
       "MergedAt": "2026-02-16T14:19:21Z"
      }
     ]
    },
    {
     "Value": 0.61,
     "PRs": [
      {
       "Number": 16852,
       "MergedAt": "2026-02-20T00:55:31Z"
      }
     ]
    },
    {
     "Value": 1.29,
     "PRs": [
      {
       "Number": 16824,
       "MergedAt": "2026-02-13T19:55:25Z"
      }
     ]
    },
    {
     "Value": 0.27,
     "PRs": [
      {
       "Number": 16810,
       "MergedAt": "2026-02-15T12:03:18Z"
      }
     ]
    },
    {
     "Value": 1.93,
     "PRs": [
      {
       "Number": 16359,
       "MergedAt": "2026-02-18T11:05:23Z"
      }
     ]
    },
    {
     "Value": 0.34,
     "PRs": [
      {
       "Number": 16859,
       "MergedAt": "2026-02-16T22:59:21Z"
      }
     ]
    },
    {
     "Value": 0.38,
     "PRs": [
      {
       "Number": 16840,
       "MergedAt": "2026-02-16T19:19:21Z"
      }
     ]
    },
    {
     "Value": 0.85,
     "PRs": [
      {
       "Number": 16820,
       "MergedAt": "2026-02-18T11:05:31Z"
      }
     ]
    },
    {
     "Value": 1.25,
     "PRs": [
      {
       "Number": 16666,
       "MergedAt": "2026-02-13T19:55:18Z"
      }
     ]
    },
    {
     "Value": 0.37,
     "PRs": [
      {
       "Number": 16875,
       "MergedAt": "2026-02-19T19:19:31Z"
      }
     ]
    },
    {
     "Value": 0.89,
     "PRs": [
      {
       "Number": 16855,
       "MergedAt": "2026-02-17T05:31:36Z"
      }
     ]
    },
    {
     "Value": 0.41,
     "PRs": [
      {
       "Number": 16833,
       "MergedAt": "2026-02-19T19:19:23Z"
      }
     ]
    },
    {
     "Value": 1.48,
     "PRs": [
      {
       "Number": 16818,
       "MergedAt": "2026-02-20T00:55:23Z"
      }
     ]
    }
   ]
  },
  "PRsMergedWithNoRetest": {
   "Avg": 0,
   "Std": 0,
   "Number": 35,
   "NoRetest": 12,
   "SIGComputeRetest": 0,
   "SIGStorageRetest": 0,
   "SIGNetworkRetest": 0,
   "SIGOperatorRetest": 0,
   "SIGCIRetest": 0,
   "SIGMonitoringRetest": 0,
   "SIGComputeTotal": 0,
   "SIGStorageTotal": 0,
   "SIGNetworkTotal": 0,
   "SIGOperatorTotal": 0,
   "SIGCITotal": 0,
   "SIGMonitoringTotal": 0,
   "QuarantineTotal": 0,
   "QuarantineSigCompute": 0,
   "QuarantineSigNetwork": 0,
   "QuarantineSigStorage": 0,
   "QuarantineSigMonitoring": 0,
   "FailedJobLeaderBoard": null,
   "DataPoints": [
    {
     "Value": 0,
     "PRs": [
      {
       "Number": 16834,
       "MergedAt": "2026-02-16T14:25:26Z"
      }
     ]
    },
    {
     "Value": 0,
     "PRs": [
      {
       "Number": 16859,
       "MergedAt": "2026-02-16T22:59:21Z"
      }
     ]
    },
    {
     "Value": 0,
     "PRs": [
      {
       "Number": 16835,
       "MergedAt": "2026-02-16T14:25:26Z"
      }
     ]
    },
    {
     "Value": 0,
     "PRs": [
      {
       "Number": 16873,
       "MergedAt": "2026-02-17T08:17:23Z"
      }
     ]
    },
    {
     "Value": 0,
     "PRs": [
      {
       "Number": 16831,
       "MergedAt": "2026-02-16T14:25:25Z"
      }
     ]
    },
    {
     "Value": 0,
     "PRs": [
      {
       "Number": 16845,
       "MergedAt": "2026-02-16T22:59:28Z"
      }
     ]
    },
    {
     "Value": 0,
     "PRs": [
      {
       "Number": 16840,
       "MergedAt": "2026-02-16T19:19:21Z"
      }
     ]
    },
    {
     "Value": 0,
     "PRs": [
      {
       "Number": 16475,
       "MergedAt": "2026-02-15T18:55:18Z"
      }
     ]
    },
    {
     "Value": 0,
     "PRs": [
      {
       "Number": 16851,
       "MergedAt": "2026-02-15T18:55:25Z"
      }
     ]
    },
    {
     "Value": 0,
     "PRs": [
      {
       "Number": 16843,
       "MergedAt": "2026-02-17T05:31:28Z"
      }
     ]
    },
    {
     "Value": 0,
     "PRs": [
      {
       "Number": 16839,
       "MergedAt": "2026-02-16T14:37:26Z"
      }
     ]
    },
    {
     "Value": 0,
     "PRs": [
      {
       "Number": 16838,
       "MergedAt": "2026-02-16T15:35:23Z"
      }
     ]
    }
   ]
  },
  "QuarantineStats": {
   "Avg": 17,
   "Std": 0,
   "Number": 0,
   "NoRetest": 0,
   "SIGComputeRetest": 0,
   "SIGStorageRetest": 0,
   "SIGNetworkRetest": 0,
   "SIGOperatorRetest": 0,
   "SIGCIRetest": 0,
   "SIGMonitoringRetest": 0,
   "SIGComputeTotal": 0,
   "SIGStorageTotal": 0,
   "SIGNetworkTotal": 0,
   "SIGOperatorTotal": 0,
   "SIGCITotal": 0,
   "SIGMonitoringTotal": 0,
   "QuarantineTotal": 17,
   "QuarantineSigCompute": 10,
   "QuarantineSigNetwork": 0,
   "QuarantineSigStorage": 5,
   "QuarantineSigMonitoring": 2,
   "FailedJobLeaderBoard": null,
   "DataPoints": [
    {
     "Value": 17,
     "Date": "2026-02-20T18:13:23Z"
    }
   ]
  },
  "SIGRetests": {
   "Avg": 0,
   "Std": 0,
   "Number": 0,
   "NoRetest": 0,
   "SIGComputeRetest": 25,
   "SIGStorageRetest": 9,
   "SIGNetworkRetest": 1,
   "SIGOperatorRetest": 5,
   "SIGCIRetest": 10,
   "SIGMonitoringRetest": 1,
   "SIGComputeTotal": 258,
   "SIGStorageTotal": 101,
   "SIGNetworkTotal": 143,
   "SIGOperatorTotal": 91,
   "SIGCITotal": 608,
   "SIGMonitoringTotal": 5,
   "QuarantineTotal": 0,
   "QuarantineSigCompute": 0,
   "QuarantineSigNetwork": 0,
   "QuarantineSigStorage": 0,
   "QuarantineSigMonitoring": 0,
   "FailedJobLeaderBoard": [
    {
     "JobName": "pull-kubevirt-e2e-k8s-1.34-sig-compute-serial",
     "FailureCount": 10,
     "SuccessCount": 34,
     "FailureURLs": [
      "https://prow.ci.kubevirt.io//view/gs/kubevirt-prow/pr-logs/pull/kubevirt_kubevirt/16855/pull-kubevirt-e2e-k8s-1.34-sig-compute-serial/2023342595807121408",
      "https://prow.ci.kubevirt.io//view/gs/kubevirt-prow/pr-logs/pull/kubevirt_kubevirt/16855/pull-kubevirt-e2e-k8s-1.34-sig-compute-serial/2022950638844907520",
      "https://prow.ci.kubevirt.io//view/gs/kubevirt-prow/pr-logs/pull/kubevirt_kubevirt/16833/pull-kubevirt-e2e-k8s-1.34-sig-compute-serial/2023838713724801024",
      "https://prow.ci.kubevirt.io//view/gs/kubevirt-prow/pr-logs/pull/kubevirt_kubevirt/16833/pull-kubevirt-e2e-k8s-1.34-sig-compute-serial/2023712208181006336",
      "https://prow.ci.kubevirt.io//view/gs/kubevirt-prow/pr-logs/pull/kubevirt_kubevirt/16758/pull-kubevirt-e2e-k8s-1.34-sig-compute-serial/2019863192468983808",
      "https://prow.ci.kubevirt.io//view/gs/kubevirt-prow/pr-logs/pull/kubevirt_kubevirt/16722/pull-kubevirt-e2e-k8s-1.34-sig-compute-serial/2022601907318558720",
      "https://prow.ci.kubevirt.io//view/gs/kubevirt-prow/pr-logs/pull/kubevirt_kubevirt/16722/pull-kubevirt-e2e-k8s-1.34-sig-compute-serial/2022480614011179008",
      "https://prow.ci.kubevirt.io//view/gs/kubevirt-prow/pr-logs/pull/kubevirt_kubevirt/16722/pull-kubevirt-e2e-k8s-1.34-sig-compute-serial/2018369550835257344",
      "https://prow.ci.kubevirt.io//view/gs/kubevirt-prow/pr-logs/pull/kubevirt_kubevirt/16658/pull-kubevirt-e2e-k8s-1.34-sig-compute-serial/2021271327393976320",
      "https://prow.ci.kubevirt.io//view/gs/kubevirt-prow/pr-logs/pull/kubevirt_kubevirt/16658/pull-kubevirt-e2e-k8s-1.34-sig-compute-serial/2021153054690119680"
     ]
    },
    {
     "JobName": "pull-kubevirt-e2e-k8s-1.34-sig-compute",
     "FailureCount": 4,
     "SuccessCount": 32,
     "FailureURLs": [
      "https://prow.ci.kubevirt.io//view/gs/kubevirt-prow/pr-logs/pull/kubevirt_kubevirt/16857/pull-kubevirt-e2e-k8s-1.34-sig-compute/2023073311763730432",
      "https://prow.ci.kubevirt.io//view/gs/kubevirt-prow/pr-logs/pull/kubevirt_kubevirt/16758/pull-kubevirt-e2e-k8s-1.34-sig-compute/2022510926996967424",
      "https://prow.ci.kubevirt.io//view/gs/kubevirt-prow/pr-logs/pull/kubevirt_kubevirt/16758/pull-kubevirt-e2e-k8s-1.34-sig-compute/2022405130044837888",
      "https://prow.ci.kubevirt.io//view/gs/kubevirt-prow/pr-logs/pull/kubevirt_kubevirt/16722/pull-kubevirt-e2e-k8s-1.34-sig-compute/2018369549157535744"
     ]
    },
    {
     "JobName": "pull-kubevirt-e2e-k8s-1.33-sig-storage",
     "FailureCount": 4,
     "SuccessCount": 27,
     "FailureURLs": [
      "https://prow.ci.kubevirt.io//view/gs/kubevirt-prow/pr-logs/pull/kubevirt_kubevirt/16875/pull-kubevirt-e2e-k8s-1.33-sig-storage/2023753669043818496",
      "https://prow.ci.kubevirt.io//view/gs/kubevirt-prow/pr-logs/pull/kubevirt_kubevirt/16820/pull-kubevirt-e2e-k8s-1.33-sig-storage/2023576575370334208",
      "https://prow.ci.kubevirt.io//view/gs/kubevirt-prow/pr-logs/pull/kubevirt_kubevirt/16666/pull-kubevirt-e2e-k8s-1.33-sig-storage/2021945165790318592",
      "https://prow.ci.kubevirt.io//view/gs/kubevirt-prow/pr-logs/pull/kubevirt_kubevirt/16655/pull-kubevirt-e2e-k8s-1.33-sig-storage/2021998298461638656"
     ]
    },
    {
     "JobName": "pull-kubevirt-e2e-k8s-1.35-sig-compute-migrations",
     "FailureCount": 4,
     "SuccessCount": 8,
     "FailureURLs": [
      "https://prow.ci.kubevirt.io//view/gs/kubevirt-prow/pr-logs/pull/kubevirt_kubevirt/16833/pull-kubevirt-e2e-k8s-1.35-sig-compute-migrations/2024203418389712896",
      "https://prow.ci.kubevirt.io//view/gs/kubevirt-prow/pr-logs/pull/kubevirt_kubevirt/16818/pull-kubevirt-e2e-k8s-1.35-sig-compute-migrations/2024219951849541632",
      "https://prow.ci.kubevirt.io//view/gs/kubevirt-prow/pr-logs/pull/kubevirt_kubevirt/16792/pull-kubevirt-e2e-k8s-1.35-sig-compute-migrations/2024223267501379584",
      "https://prow.ci.kubevirt.io//view/gs/kubevirt-prow/pr-logs/pull/kubevirt_kubevirt/16656/pull-kubevirt-e2e-k8s-1.35-sig-compute-migrations/2024224821063192576"
     ]
    },
    {
     "JobName": "pull-kubevirt-e2e-k8s-1.34-sig-compute-arm64",
     "FailureCount": 4,
     "SuccessCount": 30,
     "FailureURLs": [
      "https://prow.ci.kubevirt.io//view/gs/kubevirt-prow/pr-logs/pull/kubevirt_kubevirt/16824/pull-kubevirt-e2e-k8s-1.34-sig-compute-arm64/2021921600764383232",
      "https://prow.ci.kubevirt.io//view/gs/kubevirt-prow/pr-logs/pull/kubevirt_kubevirt/16818/pull-kubevirt-e2e-k8s-1.34-sig-compute-arm64/2024210940798439424",
      "https://prow.ci.kubevirt.io//view/gs/kubevirt-prow/pr-logs/pull/kubevirt_kubevirt/16818/pull-kubevirt-e2e-k8s-1.34-sig-compute-arm64/2024108658027139072",
      "https://prow.ci.kubevirt.io//view/gs/kubevirt-prow/pr-logs/pull/kubevirt_kubevirt/16658/pull-kubevirt-e2e-k8s-1.34-sig-compute-arm64/2020893992060719104"
     ]
    },
    {
     "JobName": "pull-kubevirt-e2e-k8s-1.34-sig-compute-migrations",
     "FailureCount": 3,
     "SuccessCount": 24,
     "FailureURLs": [
      "https://prow.ci.kubevirt.io//view/gs/kubevirt-prow/pr-logs/pull/kubevirt_kubevirt/16857/pull-kubevirt-e2e-k8s-1.34-sig-compute-migrations/2023073307519094784",
      "https://prow.ci.kubevirt.io//view/gs/kubevirt-prow/pr-logs/pull/kubevirt_kubevirt/16818/pull-kubevirt-e2e-k8s-1.34-sig-compute-migrations/2024089609390002176",
      "https://prow.ci.kubevirt.io//view/gs/kubevirt-prow/pr-logs/pull/kubevirt_kubevirt/16810/pull-kubevirt-e2e-k8s-1.34-sig-compute-migrations/2022234000239628288"
     ]
    },
    {
     "JobName": "pull-kubevirt-e2e-k8s-1.32-sig-compute",
     "FailureCount": 3,
     "SuccessCount": 22,
     "FailureURLs": [
      "https://prow.ci.kubevirt.io//view/gs/kubevirt-prow/pr-logs/pull/kubevirt_kubevirt/16819/pull-kubevirt-e2e-k8s-1.32-sig-compute/2022420232039043072",
      "https://prow.ci.kubevirt.io//view/gs/kubevirt-prow/pr-logs/pull/kubevirt_kubevirt/16810/pull-kubevirt-e2e-k8s-1.32-sig-compute/2022302611226497024",
      "https://prow.ci.kubevirt.io//view/gs/kubevirt-prow/pr-logs/pull/kubevirt_kubevirt/16758/pull-kubevirt-e2e-k8s-1.32-sig-compute/2021973727087955968"
     ]
    },
    {
     "JobName": "pull-kubevirt-e2e-k8s-1.34-sig-storage",
     "FailureCount": 3,
     "SuccessCount": 27,
     "FailureURLs": [
      "https://prow.ci.kubevirt.io//view/gs/kubevirt-prow/pr-logs/pull/kubevirt_kubevirt/16792/pull-kubevirt-e2e-k8s-1.34-sig-storage/2021962516887769088",
      "https://prow.ci.kubevirt.io//view/gs/kubevirt-prow/pr-logs/pull/kubevirt_kubevirt/16658/pull-kubevirt-e2e-k8s-1.34-sig-storage/2020954013700198400",
      "https://prow.ci.kubevirt.io//view/gs/kubevirt-prow/pr-logs/pull/kubevirt_kubevirt/16359/pull-kubevirt-e2e-k8s-1.34-sig-storage/2023390467877507072"
     ]
    },
    {
     "JobName": "pull-kubevirt-e2e-k8s-1.35-sig-compute-serial",
     "FailureCount": 2,
     "SuccessCount": 6,
     "FailureURLs": [
      "https://prow.ci.kubevirt.io//view/gs/kubevirt-prow/pr-logs/pull/kubevirt_kubevirt/16875/pull-kubevirt-e2e-k8s-1.35-sig-compute-serial/2024140689566076928",
      "https://prow.ci.kubevirt.io//view/gs/kubevirt-prow/pr-logs/pull/kubevirt_kubevirt/16857/pull-kubevirt-e2e-k8s-1.35-sig-compute-serial/2024310940563935232"
     ]
    },
    {
     "JobName": "pull-kubevirt-e2e-k8s-1.32-sig-storage-1.7",
     "FailureCount": 2,
     "SuccessCount": 2,
     "FailureURLs": [
      "https://prow.ci.kubevirt.io//view/gs/kubevirt-prow/pr-logs/pull/kubevirt_kubevirt/16311/pull-kubevirt-e2e-k8s-1.32-sig-storage-1.7/2022677421710381056",
      "https://prow.ci.kubevirt.io//view/gs/kubevirt-prow/pr-logs/pull/kubevirt_kubevirt/16311/pull-kubevirt-e2e-k8s-1.32-sig-storage-1.7/2022586559403921408"
     ]
    },
    {
     "JobName": "pull-kubevirt-e2e-k8s-1.33-sig-compute",
     "FailureCount": 2,
     "SuccessCount": 27,
     "FailureURLs": [
      "https://prow.ci.kubevirt.io//view/gs/kubevirt-prow/pr-logs/pull/kubevirt_kubevirt/16818/pull-kubevirt-e2e-k8s-1.33-sig-compute/2024113434760581120",
      "https://prow.ci.kubevirt.io//view/gs/kubevirt-prow/pr-logs/pull/kubevirt_kubevirt/16658/pull-kubevirt-e2e-k8s-1.33-sig-compute/2020870038331854848"
     ]
    },
    {
     "JobName": "pull-kubevirt-e2e-k8s-1.32-sig-operator-1.7",
     "FailureCount": 1,
     "SuccessCount": 1,
     "FailureURLs": [
      "https://prow.ci.kubevirt.io//view/gs/kubevirt-prow/pr-logs/pull/kubevirt_kubevirt/16311/pull-kubevirt-e2e-k8s-1.32-sig-operator-1.7/1998353048052699136"
     ]
    },
    {
     "JobName": "pull-kubevirt-e2e-k8s-1.34-sig-operator",
     "FailureCount": 1,
     "SuccessCount": 28,
     "FailureURLs": [
      "https://prow.ci.kubevirt.io//view/gs/kubevirt-prow/pr-logs/pull/kubevirt_kubevirt/16656/pull-kubevirt-e2e-k8s-1.34-sig-operator/2023763231184523264"
     ]
    },
    {
     "JobName": "pull-kubevirt-e2e-k8s-1.32-sig-operator",
     "FailureCount": 1,
     "SuccessCount": 19,
     "FailureURLs": [
      "https://prow.ci.kubevirt.io//view/gs/kubevirt-prow/pr-logs/pull/kubevirt_kubevirt/16758/pull-kubevirt-e2e-k8s-1.32-sig-operator/2021973727201202176"
     ]
    },
    {
     "JobName": "pull-kubevirt-e2e-k8s-1.34-sig-monitoring",
     "FailureCount": 1,
     "SuccessCount": 4,
     "FailureURLs": [
      "https://prow.ci.kubevirt.io//view/gs/kubevirt-prow/pr-logs/pull/kubevirt_kubevirt/16635/pull-kubevirt-e2e-k8s-1.34-sig-monitoring/2021337078641463296"
     ]
    },
    {
     "JobName": "pull-kubevirt-e2e-k8s-1.33-sig-operator-1.7",
     "FailureCount": 1,
     "SuccessCount": 1,
     "FailureURLs": [
      "https://prow.ci.kubevirt.io//view/gs/kubevirt-prow/pr-logs/pull/kubevirt_kubevirt/16311/pull-kubevirt-e2e-k8s-1.33-sig-operator-1.7/1998353051412336640"
     ]
    },
    {
     "JobName": "pull-kubevirt-e2e-k8s-1.34-sig-network",
     "FailureCount": 1,
     "SuccessCount": 27,
     "FailureURLs": [
      "https://prow.ci.kubevirt.io//view/gs/kubevirt-prow/pr-logs/pull/kubevirt_kubevirt/16824/pull-kubevirt-e2e-k8s-1.34-sig-network/2021909154788020224"
     ]
    },
    {
     "JobName": "pull-kubevirt-e2e-kind-1.34-sev",
     "FailureCount": 1,
     "SuccessCount": 27,
     "FailureURLs": [
      "https://prow.ci.kubevirt.io//view/gs/kubevirt-prow/pr-logs/pull/kubevirt_kubevirt/16820/pull-kubevirt-e2e-kind-1.34-sev/2023321397278806016"
     ]
    },
    {
     "JobName": "pull-kubevirt-e2e-k8s-1.35-sig-storage",
     "FailureCount": 1,
     "SuccessCount": 5,
     "FailureURLs": [
      "https://prow.ci.kubevirt.io//view/gs/kubevirt-prow/pr-logs/pull/kubevirt_kubevirt/16857/pull-kubevirt-e2e-k8s-1.35-sig-storage/2024310942258434048"
     ]
    },
    {
     "JobName": "pull-kubevirt-e2e-k8s-1.33-sig-network",
     "FailureCount": 1,
     "SuccessCount": 26,
     "FailureURLs": [
      "https://prow.ci.kubevirt.io//view/gs/kubevirt-prow/pr-logs/pull/kubevirt_kubevirt/16658/pull-kubevirt-e2e-k8s-1.33-sig-network/2020870037857898496"
     ]
    },
    {
     "JobName": "pull-kubevirt-e2e-k8s-1.34-sig-operator-1.7",
     "FailureCount": 1,
     "SuccessCount": 1,
     "FailureURLs": [
      "https://prow.ci.kubevirt.io//view/gs/kubevirt-prow/pr-logs/pull/kubevirt_kubevirt/16311/pull-kubevirt-e2e-k8s-1.34-sig-operator-1.7/1998353054767779840"
     ]
    }
   ],
   "DataPoints": [
    {
     "Value": 2,
     "PRs": [
      {
       "Number": 16875,
       "MergedAt": "2026-02-19T19:19:31Z"
      }
     ]
    },
    {
     "Value": 0,
     "PRs": [
      {
       "Number": 16873,
       "MergedAt": "2026-02-17T08:17:23Z"
      }
     ]
    },
    {
     "Value": 0,
     "PRs": [
      {
       "Number": 16859,
       "MergedAt": "2026-02-16T22:59:21Z"
      }
     ]
    },
    {
     "Value": 4,
     "PRs": [
      {
       "Number": 16857,
       "MergedAt": "2026-02-19T11:21:32Z"
      }
     ]
    },
    {
     "Value": 2,
     "PRs": [
      {
       "Number": 16855,
       "MergedAt": "2026-02-17T05:31:36Z"
      }
     ]
    },
    {
     "Value": 0,
     "PRs": [
      {
       "Number": 16852,
       "MergedAt": "2026-02-20T00:55:31Z"
      }
     ]
    },
    {
     "Value": 0,
     "PRs": [
      {
       "Number": 16851,
       "MergedAt": "2026-02-15T18:55:25Z"
      }
     ]
    },
    {
     "Value": 0,
     "PRs": [
      {
       "Number": 16850,
       "MergedAt": "2026-02-20T06:35:30Z"
      }
     ]
    },
    {
     "Value": 0,
     "PRs": [
      {
       "Number": 16847,
       "MergedAt": "2026-02-14T17:33:17Z"
      }
     ]
    },
    {
     "Value": 0,
     "PRs": [
      {
       "Number": 16845,
       "MergedAt": "2026-02-16T22:59:28Z"
      }
     ]
    },
    {
     "Value": 0,
     "PRs": [
      {
       "Number": 16843,
       "MergedAt": "2026-02-17T05:31:28Z"
      }
     ]
    },
    {
     "Value": 0,
     "PRs": [
      {
       "Number": 16840,
       "MergedAt": "2026-02-16T19:19:21Z"
      }
     ]
    },
    {
     "Value": 0,
     "PRs": [
      {
       "Number": 16839,
       "MergedAt": "2026-02-16T14:37:26Z"
      }
     ]
    },
    {
     "Value": 0,
     "PRs": [
      {
       "Number": 16838,
       "MergedAt": "2026-02-16T15:35:23Z"
      }
     ]
    },
    {
     "Value": 0,
     "PRs": [
      {
       "Number": 16837,
       "MergedAt": "2026-02-16T10:11:20Z"
      }
     ]
    },
    {
     "Value": 0,
     "PRs": [
      {
       "Number": 16835,
       "MergedAt": "2026-02-16T14:25:26Z"
      }
     ]
    },
    {
     "Value": 0,
     "PRs": [
      {
       "Number": 16834,
       "MergedAt": "2026-02-16T14:25:26Z"
      }
     ]
    },
    {
     "Value": 3,
     "PRs": [
      {
       "Number": 16833,
       "MergedAt": "2026-02-19T19:19:23Z"
      }
     ]
    },
    {
     "Value": 0,
     "PRs": [
      {
       "Number": 16831,
       "MergedAt": "2026-02-16T14:25:25Z"
      }
     ]
    },
    {
     "Value": 2,
     "PRs": [
      {
       "Number": 16824,
       "MergedAt": "2026-02-13T19:55:25Z"
      }
     ]
    },
    {
     "Value": 2,
     "PRs": [
      {
       "Number": 16820,
       "MergedAt": "2026-02-18T11:05:31Z"
      }
     ]
    },
    {
     "Value": 1,
     "PRs": [
      {
       "Number": 16819,
       "MergedAt": "2026-02-14T12:35:18Z"
      }
     ]
    },
    {
     "Value": 5,
     "PRs": [
      {
       "Number": 16818,
       "MergedAt": "2026-02-20T00:55:23Z"
      }
     ]
    },
    {
     "Value": 2,
     "PRs": [
      {
       "Number": 16810,
       "MergedAt": "2026-02-15T12:03:18Z"
      }
     ]
    },
    {
     "Value": 2,
     "PRs": [
      {
       "Number": 16792,
       "MergedAt": "2026-02-19T11:21:24Z"
      }
     ]
    },
    {
     "Value": 5,
     "PRs": [
      {
       "Number": 16758,
       "MergedAt": "2026-02-16T14:19:21Z"
      }
     ]
    },
    {
     "Value": 4,
     "PRs": [
      {
       "Number": 16722,
       "MergedAt": "2026-02-16T07:11:19Z"
      }
     ]
    },
    {
     "Value": 1,
     "PRs": [
      {
       "Number": 16666,
       "MergedAt": "2026-02-13T19:55:18Z"
      }
     ]
    },
    {
     "Value": 6,
     "PRs": [
      {
       "Number": 16658,
       "MergedAt": "2026-02-17T05:31:21Z"
      }
     ]
    },
    {
     "Value": 2,
     "PRs": [
      {
       "Number": 16656,
       "MergedAt": "2026-02-20T06:35:23Z"
      }
     ]
    },
    {
     "Value": 1,
     "PRs": [
      {
       "Number": 16655,
       "MergedAt": "2026-02-16T22:59:21Z"
      }
     ]
    },
    {
     "Value": 1,
     "PRs": [
      {
       "Number": 16635,
       "MergedAt": "2026-02-14T05:35:18Z"
      }
     ]
    },
    {
     "Value": 0,
     "PRs": [
      {
       "Number": 16475,
       "MergedAt": "2026-02-15T18:55:18Z"
      }
     ]
    },
    {
     "Value": 1,
     "PRs": [
      {
       "Number": 16359,
       "MergedAt": "2026-02-18T11:05:23Z"
      }
     ]
    },
    {
     "Value": 5,
     "PRs": [
      {
       "Number": 16311,
       "MergedAt": "2026-02-20T08:27:25Z"
      }
     ]
    }
   ]
  }
 }
}