{
 "EndDate": "2021-09-28T10:20:57Z",
 "DataDays": 7,
 "Source": "kubevirt/kubevirt",
 "Data": {
  "AverageMergeQueueLength": {
   "Avg": 2.14,
   "Std": 2.53,
   "DataPoints": [
    {
     "Value": 8,
     "Date": "2021-09-28T10:20:57Z",
     "PRs": [
      {
       "Number": 6461,
       "MergedAt": "0001-01-01T00:00:00Z"
      },
      {
       "Number": 6458,
       "MergedAt": "0001-01-01T00:00:00Z"
      },
      {
       "Number": 6453,
       "MergedAt": "0001-01-01T00:00:00Z"
      },
      {
       "Number": 6452,
       "MergedAt": "0001-01-01T00:00:00Z"
      },
      {
       "Number": 6439,
       "MergedAt": "0001-01-01T00:00:00Z"
      },
      {
       "Number": 6366,
       "MergedAt": "0001-01-01T00:00:00Z"
      },
      {
       "Number": 6336,
       "MergedAt": "0001-01-01T00:00:00Z"
      },
      {
       "Number": 6329,
       "MergedAt": "0001-01-01T00:00:00Z"
      }
     ]
    },
    {
     "Value": 2,
     "Date": "2021-09-27T10:20:57Z",
     "PRs": [
      {
       "Number": 6452,
       "MergedAt": "0001-01-01T00:00:00Z"
      },
      {
       "Number": 6329,
       "MergedAt": "0001-01-01T00:00:00Z"
      }
     ]
    },
    {
     "Value": 0,
     "Date": "2021-09-26T10:20:57Z"
    },
    {
     "Value": 1,
     "Date": "2021-09-25T10:20:57Z",
     "PRs": [
      {
       "Number": 6112,
       "MergedAt": "2021-09-25T16:17:29Z"
      }
     ]
    },
    {
     "Value": 2,
     "Date": "2021-09-24T10:20:57Z",
     "PRs": [
      {
       "Number": 6450,
       "MergedAt": "2021-09-24T11:33:25Z"
      },
      {
       "Number": 6285,
       "MergedAt": "2021-09-24T18:25:34Z"
      }
     ]
    },
    {
     "Value": 2,
     "Date": "2021-09-23T10:20:57Z",
     "PRs": [
      {
       "Number": 6434,
       "MergedAt": "2021-09-23T15:28:54Z"
      },
      {
       "Number": 6408,
       "MergedAt": "2021-09-23T11:48:49Z"
      }
     ]
    },
    {
     "Value": 0,
     "Date": "2021-09-22T10:20:57Z"
    }
   ]
  },
  "AverageMergedPRs": {
   "Avg": 2,
   "Std": 0,
   "DataPoints": [
    {
     "Value": 1,
     "PRs": [
      {
       "Number": 6463,
       "MergedAt": "2021-09-28T00:59:33Z"
      }
     ]
    },
    {
     "Value": 1,
     "PRs": [
      {
       "Number": 6451,
       "MergedAt": "2021-09-23T07:30:42Z"
      }
     ]
    },
    {
     "Value": 1,
     "PRs": [
      {
       "Number": 6450,
       "MergedAt": "2021-09-24T11:33:25Z"
      }
     ]
    },
    {
     "Value": 1,
     "PRs": [
      {
       "Number": 6446,
       "MergedAt": "2021-09-27T21:38:06Z"
      }
     ]
    },
    {
     "Value": 1,
     "PRs": [
      {
       "Number": 6443,
       "MergedAt": "2021-09-21T12:35:49Z"
      }
     ]
    },
    {
     "Value": 1,
     "PRs": [
      {
       "Number": 6441,
       "MergedAt": "2021-09-21T16:44:03Z"
      }
     ]
    },
    {
     "Value": 1,
     "PRs": [
      {
       "Number": 6434,
       "MergedAt": "2021-09-23T15:28:54Z"
      }
     ]
    },
    {
     "Value": 1,
     "PRs": [
      {
       "Number": 6433,
       "MergedAt": "2021-09-21T19:38:23Z"
      }
     ]
    },
    {
     "Value": 1,
     "PRs": [
      {
       "Number": 6415,
       "MergedAt": "2021-09-27T08:04:34Z"
      }
     ]
    },
    {
     "Value": 1,
     "PRs": [
      {
       "Number": 6409,
       "MergedAt": "2021-09-24T21:13:27Z"
      }
     ]
    },
    {
     "Value": 1,
     "PRs": [
      {
       "Number": 6408,
       "MergedAt": "2021-09-23T11:48:49Z"
      }
     ]
    },
    {
     "Value": 1,
     "PRs": [
      {
       "Number": 6333,
       "MergedAt": "2021-09-27T13:11:32Z"
      }
     ]
    },
    {
     "Value": 1,
     "PRs": [
      {
       "Number": 6285,
       "MergedAt": "2021-09-24T18:25:34Z"
      }
     ]
    },
    {
     "Value": 1,
     "PRs": [
      {
       "Number": 6112,
       "MergedAt": "2021-09-25T16:17:29Z"
      }
     ]
    }
   ]
  },
  "AverageRetestsToMerge": {
   "Avg": 3.86,
   "Std": 5.1,
   "DataPoints": [
    {
     "Value": 1,
     "PRs": [
      {
       "Number": 6446,
       "MergedAt": "2021-09-27T21:38:06Z"
      }
     ]
    },
    {
     "Value": 1,
     "PRs": [
      {
       "Number": 6443,
       "MergedAt": "2021-09-21T12:35:49Z"
      }
     ]
    },
    {
     "Value": 1,
     "PRs": [
      {
       "Number": 6433,
       "MergedAt": "2021-09-21T19:38:23Z"
      }
     ]
    },
    {
     "Value": 2,
     "PRs": [
      {
       "Number": 6285,
       "MergedAt": "2021-09-24T18:25:34Z"
      }
     ]
    },
    {
     "Value": 19,
     "PRs": [
      {
       "Number": 6112,
       "MergedAt": "2021-09-25T16:17:29Z"
      }
     ]
    },
    {
     "Value": 2,
     "PRs": [
      {
       "Number": 6463,
       "MergedAt": "2021-09-28T00:59:33Z"
      }
     ]
    },
    {
     "Value": 12,
     "PRs": [
      {
       "Number": 6434,
       "MergedAt": "2021-09-23T15:28:54Z"
      }
     ]
    },
    {
     "Value": 4,
     "PRs": [
      {
       "Number": 6409,
       "MergedAt": "2021-09-24T21:13:27Z"
      }
     ]
    },
    {
     "Value": 0,
     "PRs": [
      {
       "Number": 6408,
       "MergedAt": "2021-09-23T11:48:49Z"
      }
     ]
    },
    {
     "Value": 1,
     "PRs": [
      {
       "Number": 6451,
       "MergedAt": "2021-09-23T07:30:42Z"
      }
     ]
    },
    {
     "Value": 2,
     "PRs": [
      {
       "Number": 6441,
       "MergedAt": "2021-09-21T16:44:03Z"
      }
     ]
    },
    {
     "Value": 1,
     "PRs": [
      {
       "Number": 6450,
       "MergedAt": "2021-09-24T11:33:25Z"
      }
     ]
    },
    {
     "Value": 5,
     "PRs": [
      {
       "Number": 6333,
       "MergedAt": "2021-09-27T13:11:32Z"
      }
     ]
    },
    {
     "Value": 3,
     "PRs": [
      {
       "Number": 6415,
       "MergedAt": "2021-09-27T08:04:34Z"
      }
     ]
    }
   ]
  },
  "AverageTimeToMerge": {
   "Avg": 0.24,
   "Std": 0.26,
   "DataPoints": [
    {
     "Value": 0.27,
     "PRs": [
      {
       "Number": 6463,
       "MergedAt": "2021-09-28T00:59:33Z"
      }
     ]
    },
    {
     "Value": 0.03,
     "PRs": [
      {
       "Number": 6443,
       "MergedAt": "2021-09-21T12:35:49Z"
      }
     ]
    },
    {
     "Value": 0.24,
     "PRs": [
      {
       "Number": 6450,
       "MergedAt": "2021-09-24T11:33:25Z"
      }
     ]
    },
    {
     "Value": 0.33,
     "PRs": [
      {
       "Number": 6434,
       "MergedAt": "2021-09-23T15:28:54Z"
      }
     ]
    },
    {
     "Value": 0.49,
     "PRs": [
      {
       "Number": 6433,
       "MergedAt": "2021-09-21T19:38:23Z"
      }
     ]
    },
    {
     "Value": 0.15,
     "PRs": [
      {
       "Number": 6408,
       "MergedAt": "2021-09-23T11:48:49Z"
      }
     ]
    },
    {
     "Value": 0.06,
     "PRs": [
      {
       "Number": 6333,
       "MergedAt": "2021-09-27T13:11:32Z"
      }
     ]
    },
    {
     "Value": 1.02,
     "PRs": [
      {
       "Number": 6112,
       "MergedAt": "2021-09-25T16:17:29Z"
      }
     ]
    },
    {
     "Value": 0,
     "PRs": [
      {
       "Number": 6451,
       "MergedAt": "2021-09-23T07:30:42Z"
      }
     ]
    },
    {
     "Value": 0,
     "PRs": [
      {
       "Number": 6446,
       "MergedAt": "2021-09-27T21:38:06Z"
      }
     ]
    },
    {
     "Value": 0.29,
     "PRs": [
      {
       "Number": 6441,
       "MergedAt": "2021-09-21T16:44:03Z"
      }
     ]
    },
    {
     "Value": 0.02,
     "PRs": [
      {
       "Number": 6415,
       "MergedAt": "2021-09-27T08:04:34Z"
      }
     ]
    },
    {
     "Value": 0.13,
     "PRs": [
      {
       "Number": 6409,
       "MergedAt": "2021-09-24T21:13:27Z"
      }
     ]
    },
    {
     "Value": 0.39,
     "PRs": [
      {
       "Number": 6285,
       "MergedAt": "2021-09-24T18:25:34Z"
      }
     ]
    }
   ]
  }
 }
}