{
 "EndDate": "2023-09-14T09:34:47Z",
 "DataDays": 7,
 "Source": "kubevirt/kubevirt",
 "Data": {
  "AverageMergeQueueLength": {
   "Avg": 1,
   "Std": 1.31,
   "Number": 0,
   "NoRetest": 0,
   "DataPoints": [
    {
     "Value": 4,
     "Date": "2023-09-14T09:34:47Z",
     "PRs": [
      {
       "Number": 10431,
       "MergedAt": "0001-01-01T00:00:00Z"
      },
      {
       "Number": 10416,
       "MergedAt": "0001-01-01T00:00:00Z"
      },
      {
       "Number": 10408,
       "MergedAt": "0001-01-01T00:00:00Z"
      },
      {
       "Number": 10086,
       "MergedAt": "0001-01-01T00:00:00Z"
      }
     ]
    },
    {
     "Value": 1,
     "Date": "2023-09-13T09:34:47Z",
     "PRs": [
      {
       "Number": 10414,
       "MergedAt": "2023-09-14T01:37:16Z"
      }
     ]
    },
    {
     "Value": 1,
     "Date": "2023-09-12T09:34:47Z",
     "PRs": [
      {
       "Number": 10406,
       "MergedAt": "2023-09-12T10:03:03Z"
      }
     ]
    },
    {
     "Value": 0,
     "Date": "2023-09-11T09:34:47Z"
    },
    {
     "Value": 0,
     "Date": "2023-09-10T09:34:47Z"
    },
    {
     "Value": 0,
     "Date": "2023-09-09T09:34:47Z"
    },
    {
     "Value": 1,
     "Date": "2023-09-08T09:34:47Z",
     "PRs": [
      {
       "Number": 10398,
       "MergedAt": "2023-09-08T14:20:59Z"
      }
     ]
    }
   ]
  },
  "AverageMergedPRs": {
   "Avg": 2.2857142857142856,
   "Std": 0,
   "Number": 0,
   "NoRetest": 0,
   "DataPoints": [
    {
     "Value": 1,
     "PRs": [
      {
       "Number": 10421,
       "MergedAt": "2023-09-13T01:57:04Z"
      }
     ]
    },
    {
     "Value": 1,
     "PRs": [
      {
       "Number": 10417,
       "MergedAt": "2023-09-13T00:15:04Z"
      }
     ]
    },
    {
     "Value": 1,
     "PRs": [
      {
       "Number": 10414,
       "MergedAt": "2023-09-14T01:37:16Z"
      }
     ]
    },
    {
     "Value": 1,
     "PRs": [
      {
       "Number": 10406,
       "MergedAt": "2023-09-12T10:03:03Z"
      }
     ]
    },
    {
     "Value": 1,
     "PRs": [
      {
       "Number": 10405,
       "MergedAt": "2023-09-11T18:11:03Z"
      }
     ]
    },
    {
     "Value": 1,
     "PRs": [
      {
       "Number": 10402,
       "MergedAt": "2023-09-12T02:57:03Z"
      }
     ]
    },
    {
     "Value": 1,
     "PRs": [
      {
       "Number": 10398,
       "MergedAt": "2023-09-08T14:20:59Z"
      }
     ]
    },
    {
     "Value": 1,
     "PRs": [
      {
       "Number": 10397,
       "MergedAt": "2023-09-11T16:09:04Z"
      }
     ]
    },
    {
     "Value": 1,
     "PRs": [
      {
       "Number": 10394,
       "MergedAt": "2023-09-14T01:37:09Z"
      }
     ]
    },
    {
     "Value": 1,
     "PRs": [
      {
       "Number": 10391,
       "MergedAt": "2023-09-08T21:53:00Z"
      }
     ]
    },
    {
     "Value": 1,
     "PRs": [
      {
       "Number": 10386,
       "MergedAt": "2023-09-07T18:17:30Z"
      }
     ]
    },
    {
     "Value": 1,
     "PRs": [
      {
       "Number": 10382,
       "MergedAt": "2023-09-08T06:47:32Z"
      }
     ]
    },
    {
     "Value": 1,
     "PRs": [
      {
       "Number": 10370,
       "MergedAt": "2023-09-09T05:38:58Z"
      }
     ]
    },
    {
     "Value": 1,
     "PRs": [
      {
       "Number": 10362,
       "MergedAt": "2023-09-07T10:55:28Z"
      }
     ]
    },
    {
     "Value": 1,
     "PRs": [
      {
       "Number": 10337,
       "MergedAt": "2023-09-08T00:55:30Z"
      }
     ]
    },
    {
     "Value": 1,
     "PRs": [
      {
       "Number": 10050,
       "MergedAt": "2023-09-13T08:51:05Z"
      }
     ]
    }
   ]
  },
  "AverageRetestsToMerge": {
   "Avg": 1.69,
   "Std": 1.26,
   "Number": 0,
   "NoRetest": 0,
   "DataPoints": [
    {
     "Value": 1,
     "PRs": [
      {
       "Number": 10397,
       "MergedAt": "2023-09-11T16:09:04Z"
      }
     ]
    },
    {
     "Value": 2,
     "PRs": [
      {
       "Number": 10394,
       "MergedAt": "2023-09-14T01:37:09Z"
      }
     ]
    },
    {
     "Value": 2,
     "PRs": [
      {
       "Number": 10391,
       "MergedAt": "2023-09-08T21:53:00Z"
      }
     ]
    },
    {
     "Value": 2,
     "PRs": [
      {
       "Number": 10337,
       "MergedAt": "2023-09-08T00:55:30Z"
      }
     ]
    },
    {
     "Value": 5,
     "PRs": [
      {
       "Number": 10406,
       "MergedAt": "2023-09-12T10:03:03Z"
      }
     ]
    },
    {
     "Value": 1,
     "PRs": [
      {
       "Number": 10405,
       "MergedAt": "2023-09-11T18:11:03Z"
      }
     ]
    },
    {
     "Value": 3,
     "PRs": [
      {
       "Number": 10421,
       "MergedAt": "2023-09-13T01:57:04Z"
      }
     ]
    },
    {
     "Value": 1,
     "PRs": [
      {
       "Number": 10370,
       "MergedAt": "2023-09-09T05:38:58Z"
      }
     ]
    },
    {
     "Value": 3,
     "PRs": [
      {
       "Number": 10402,
       "MergedAt": "2023-09-12T02:57:03Z"
      }
     ]
    },
    {
     "Value": 0,
     "PRs": [
      {
       "Number": 10417,
       "MergedAt": "2023-09-13T00:15:04Z"
      }
     ]
    },
    {
     "Value": 1,
     "PRs": [
      {
       "Number": 10414,
       "MergedAt": "2023-09-14T01:37:16Z"
      }
     ]
    },
    {
     "Value": 1,
     "PRs": [
      {
       "Number": 10382,
       "MergedAt": "2023-09-08T06:47:32Z"
      }
     ]
    },
    {
     "Value": 1,
     "PRs": [
      {
       "Number": 10362,
       "MergedAt": "2023-09-07T10:55:28Z"
      }
     ]
    },
    {
     "Value": 3,
     "PRs": [
      {
       "Number": 10050,
       "MergedAt": "2023-09-13T08:51:05Z"
      }
     ]
    },
    {
     "Value": 1,
     "PRs": [
      {
       "Number": 10398,
       "MergedAt": "2023-09-08T14:20:59Z"
      }
     ]
    },
    {
     "Value": 0,
     "PRs": [
      {
       "Number": 10386,
       "MergedAt": "2023-09-07T18:17:30Z"
      }
     ]
    }
   ]
  },
  "AverageTimeToMerge": {
   "Avg": 0.41,
   "Std": 0.26,
   "Number": 0,
   "NoRetest": 0,
   "DataPoints": [
    {
     "Value": 0,
     "PRs": [
      {
       "Number": 10382,
       "MergedAt": "2023-09-08T06:47:32Z"
      }
     ]
    },
    {
     "Value": 0.4,
     "PRs": [
      {
       "Number": 10370,
       "MergedAt": "2023-09-09T05:38:58Z"
      }
     ]
    },
    {
     "Value": 0.24,
     "PRs": [
      {
       "Number": 10417,
       "MergedAt": "2023-09-13T00:15:04Z"
      }
     ]
    },
    {
     "Value": 0.34,
     "PRs": [
      {
       "Number": 10391,
       "MergedAt": "2023-09-08T21:53:00Z"
      }
     ]
    },
    {
     "Value": 0.49,
     "PRs": [
      {
       "Number": 10337,
       "MergedAt": "2023-09-08T00:55:30Z"
      }
     ]
    },
    {
     "Value": 0.59,
     "PRs": [
      {
       "Number": 10402,
       "MergedAt": "2023-09-12T02:57:03Z"
      }
     ]
    },
    {
     "Value": 0,
     "PRs": [
      {
       "Number": 10397,
       "MergedAt": "2023-09-11T16:09:04Z"
      }
     ]
    },
    {
     "Value": 0.31,
     "PRs": [
      {
       "Number": 10405,
       "MergedAt": "2023-09-11T18:11:03Z"
      }
     ]
    },
    {
     "Value": 0.55,
     "PRs": [
      {
       "Number": 10394,
       "MergedAt": "2023-09-14T01:37:09Z"
      }
     ]
    },
    {
     "Value": 0.46,
     "PRs": [
      {
       "Number": 10050,
       "MergedAt": "2023-09-13T08:51:05Z"
      }
     ]
    },
    {
     "Value": 0.09,
     "PRs": [
      {
       "Number": 10421,
       "MergedAt": "2023-09-13T01:57:04Z"
      }
     ]
    },
    {
     "Value": 0.71,
     "PRs": [
      {
       "Number": 10414,
       "MergedAt": "2023-09-14T01:37:16Z"
      }
     ]
    },
    {
     "Value": 0.82,
     "PRs": [
      {
       "Number": 10362,
       "MergedAt": "2023-09-07T10:55:28Z"
      }
     ]
    },
    {
     "Value": 0.85,
     "PRs": [
      {
       "Number": 10406,
       "MergedAt": "2023-09-12T10:03:03Z"
      }
     ]
    },
    {
     "Value": 0.25,
     "PRs": [
      {
       "Number": 10398,
       "MergedAt": "2023-09-08T14:20:59Z"
      }
     ]
    }
   ]
  },
  "PRsMergedWithNoRetest": {
   "Avg": 0,
   "Std": 0,
   "Number": 16,
   "NoRetest": 2,
   "DataPoints": [
    {
     "Value": 0,
     "PRs": [
      {
       "Number": 10386,
       "MergedAt": "2023-09-07T18:17:30Z"
      }
     ]
    },
    {
     "Value": 0,
     "PRs": [
      {
       "Number": 10417,
       "MergedAt": "2023-09-13T00:15:04Z"
      }
     ]
    }
   ]
  }
 }
}